moore_1011.v
module moore_1011 (
    input in, clk, rst, 
    output reg out
);
// Here the #states aris more than required in mealy, here it is 5, hence we need 3 bits to define states
parameter[2:0] s0=3'b000,s1=3'b001,s2=3'b010,s3=3'b011,s4=3'b100;
reg[2:0] ps, ns;

// Now we write the state transition logic here 

always @(*) begin
    case (ps)
        s0: if (in) begin
            ns = s1;
        end else begin
            ns = s0;
        end 
        s1: if (in) begin
            ns = s1;
        end else begin
            ns= s2;
        end
        s2: if (in) begin
            ns = s3;
        end else begin
            ns = s0;
        end
        s3: if (in) begin
            ns = s4;
        end else begin
            ns = s2;
        end
        s4: if (in) begin
            ns = s1;
        end else begin
            ns = s2;
        end
        default: ns = s0;
    endcase
end

// here we end the state transition logic
//Now we write the state memory logic 
always @(posedge clk, posedge rst) begin
    if (rst) begin
        ps <= s0;
    end else begin
        ps <= ns;
    end
end
// Now comes the output logic, unlike mealy where in the last state the output depended on Input, here all outputs are well defined
always @(*) begin
    case (ps)
        s0: out = 1'b0;
        s1: out = 1'b0;
        s2: out = 1'b0;
        s3: out = 1'b0;
        s4: out = 1'b1; 
        default: out = 1'b0; 
    endcase
    
end

endmodule

mealy_1011.v
//This is the first code that is for Mealy sequence detector of sequence 1011
module mealy_1011 ( 
    input in, clk, rst,
    output reg out
);
    parameter [1:0] s0=2'b00, s1 = 2'b01, s2=2'b10, s3=2'b11; 
    reg [1:0] ps,ns;

    //Now comes the state transition logic for the detector
always@(*) begin
    case (ps)
        s0: if (in) begin
            ns = s1;
        end else begin
            ns = s0;
        end
        s1: if (in) begin
            ns = s1;
        end else begin
            ns = s2;
        end
        s2: if (in) begin
            ns = s3;
        end else begin
            ns = s0;
        end
        s3: if (in) begin
            ns = s1;
        end else begin
            ns = s2;
        end
        default: ns = s0; 
    endcase
end

// Now we write the state memory 
always @(posedge clk, posedge rst ) begin
    if (rst) begin
        ps <= s0;
    end else begin
        ps <= ns;
    end
    
end

// Now its time to write the output logic which is the main difference between mealy and moore 

always@(*) begin
    case (ps)
        s0: out = 1'b0;
        s1: out = 1'b0;
        s2: out = 1'b0;
        s3: if (in) begin
            out = 1'b1;
        end else begin
            out = 1'b0; 
        end
        default: out = 1'b0;
    endcase
end

endmodule

mealy_moore_output_tb.v
// This stest bench will instansiate both the mealy and moore module and get the output
`timescale 1ps/1ps
`include "mealy_1011.v"
`include "moore_1011.v"

module mealy_moore_output_tb;

reg in, clk, rst;
wire mealy_out, moore_out;

mealy_1011 uut_mealy (.in(in),.clk(clk),.rst(rst),.out(mealy_out));
moore_1011 uut_moore (.in(in),.clk(clk),.rst(rst),.out(moore_out));
// Now we first generate a clk signal, here the time period of clock is 10ns
initial begin
    clk = 0;
    forever begin
        #5 clk = ~clk;
    end
end

// Now we write the test bench where we assign the test values 
initial begin
    $dumpfile("mealy_moore_output_tb.vcd");
    $dumpvars(0, mealy_moore_output_tb);
    in=0;
    rst=1;
    #10 rst = 0; // Now reset =0
    // Now I will give a correct sequence

    #10 in = 1;
    #10 in = 0;
    #10 in = 1;
    #10 in = 1;
    // If you see correct sequence was given here 
    // Now I will play with the clock, reset as well as the time 
    #5 rst = 1;
    #5 in = 1;
    #10 in = 0;
    #5 rst = 0;
    #15 in = 1;
    #15 in = 1;
    #5 in = 0;
    #10 in = 1;
    #10 in = 1;

    // Check for overlap 
    #10 in=1; #10 in=0; #10 in=1; #10 in=1; // First '1011' - should detect
    #10 in=0; #10 in=1; #10 in=1;           // Overlapping '1011' - should detect again

    // Negative Test 
    #10 in=0; #10 in=0; #10 in=1; #10 in=0; // Should NOT detect

    // Test reset in middle of sequence
    #10 rst=1; #10 rst=0; // FSM should reset here

    // Test with a noisy start
    #10 in=1; #10 in=1; #10 in=0; #10 in=1; #10 in=1; // '1', '1', then '011' - should detect at end

    // These many cases seem to be alot.

    #20 $finish;

end

// NOw we monitor the signals 
initial begin
    $monitor("in = %b | Clk = %b | reset =%b | mealy_output = %b | moore_output = %b | Time = %0t ", in, clk, rst, mealy_out, moore_out, $time);
end

endmodule

mealy_moore_output_tb.vcd
$date
	Sun Aug 03 04:24:07 2025
$end
$version
	Icarus Verilog
$end
$timescale
	1ps
$end
$scope module mealy_moore_output_tb $end
$var wire 1 ! mealy_out $end
$var wire 1 " moore_out $end
$var reg 1 # clk $end
$var reg 1 $ in $end
$var reg 1 % rst $end
$scope module uut_mealy $end
$var wire 1 & clk $end
$var wire 1 ' in $end
$var wire 1 ( rst $end
$var reg 2 ) ns [1:0] $end
$var reg 1 * out $end
$var reg 2 + ps [1:0] $end
$upscope $end
$scope module uut_moore $end
$var wire 1 & clk $end
$var wire 1 ' in $end
$var wire 1 ( rst $end
$var reg 3 , ns [2:0] $end
$var reg 1 - out $end
$var reg 3 . ps [2:0] $end
$upscope $end
$upscope $end
$enddefinitions $end
#0
$dumpvars
b0 .
0-
b0 ,
b0 +
0*
b0 )
1(
0'
0&
1%
0$
0#
0"
0!
$end
#5
1#
1&
#10
0#
0&
0%
0(
#15
1#
1&
#20
b1 ,
b1 )
0#
0&
1$
1'
#25
b1 .
b1 +
1#
1&
#30
b10 ,
b10 )
0#
0&
0$
0'
#35
b0 )
b0 ,
b10 +
b10 .
1#
1&
#40
b11 ,
b11 )
0#
0&
1$
1'
#45
b100 ,
b1 )
1*
1!
b11 .
b11 +
1#
1&
#50
0#
0&
#55
0*
0!
b1 ,
b0 +
b0 .
1#
1&
1%
1(
#60
0#
0&
#65
1#
1&
#70
b0 ,
b0 )
0#
0&
0$
0'
#75
1#
1&
0%
0(
#80
0#
0&
#85
1#
1&
#90
b1 ,
b1 )
0#
0&
1$
1'
#95
b1 +
b1 .
1#
1&
#100
0#
0&
#105
1#
1&
#110
b10 ,
b10 )
0#
0&
0$
0'
#115
b0 )
b0 ,
b10 +
b10 .
1#
1&
#120
b11 ,
b11 )
0#
0&
1$
1'
#125
b100 ,
b1 )
1*
1!
b11 .
b11 +
1#
1&
#130
0#
0&
#135
0*
0!
1-
1"
b1 ,
b1 +
b100 .
1#
1&
#140
0#
0&
#145
0-
0"
b1 .
1#
1&
#150
b10 ,
b10 )
0#
0&
0$
0'
#155
b0 )
b0 ,
b10 +
b10 .
1#
1&
#160
b11 ,
b11 )
0#
0&
1$
1'
#165
b100 ,
1*
1!
b1 )
b11 .
b11 +
1#
1&
#170
0#
0&
#175
0*
0!
1-
1"
b1 ,
b1 +
b100 .
1#
1&
#180
b10 ,
b10 )
0#
0&
0$
0'
#185
0-
0"
b0 ,
b0 )
b10 .
b10 +
1#
1&
#190
b11 ,
b11 )
0#
0&
1$
1'
#195
b1 )
1*
1!
b100 ,
b11 +
b11 .
1#
1&
#200
0#
0&
#205
1-
1"
b1 ,
0*
0!
b100 .
b1 +
1#
1&
#210
b10 ,
b10 )
0#
0&
0$
0'
#215
b0 )
0-
0"
b0 ,
b10 +
b10 .
1#
1&
#220
0#
0&
#225
b0 .
b0 +
1#
1&
#230
b1 ,
b1 )
0#
0&
1$
1'
#235
b1 +
b1 .
1#
1&
#240
b10 ,
b10 )
0#
0&
0$
0'
#245
b0 ,
b0 )
b10 .
b10 +
1#
1&
#250
b0 +
b0 .
0#
0&
1%
1(
#255
1#
1&
#260
0#
0&
0%
0(
#265
1#
1&
#270
b1 ,
b1 )
0#
0&
1$
1'
#275
b1 .
b1 +
1#
1&
#280
0#
0&
#285
1#
1&
#290
b10 ,
b10 )
0#
0&
0$
0'
#295
b0 ,
b0 )
b10 .
b10 +
1#
1&
#300
b11 ,
b11 )
0#
0&
1$
1'
#305
1*
1!
b1 )
b100 ,
b11 +
b11 .
1#
1&
#310
0#
0&
#315
1-
1"
b1 ,
0*
0!
b100 .
b1 +
1#
1&
#320
0#
0&
#325
0-
0"
b1 .
1#
1&
